hack4u_dom/__init__.py
hack4u_dom/course.py
hack4u_dom/utils.py
hack4u_dom-0.1.0.dist-info/METADATA
hack4u_dom-0.1.0.dist-info/WHEEL
hack4u_dom-0.1.0.dist-info/top_level.txt
hack4u_dom-0.1.0.dist-info/RECORD
